__init__.py
datafox.py
example.py
example_test.py
datafox-0.0.3.dist-info/LICENSE
datafox-0.0.3.dist-info/METADATA
datafox-0.0.3.dist-info/WHEEL
datafox-0.0.3.dist-info/top_level.txt
datafox-0.0.3.dist-info/RECORD
